package/__init__.py
package/main.py
woon_vconfig-0.0.1.dist-info/METADATA
woon_vconfig-0.0.1.dist-info/WHEEL
woon_vconfig-0.0.1.dist-info/top_level.txt
woon_vconfig-0.0.1.dist-info/RECORD
