Metadata-Version: 2.1
Name: woon-vconfig
Version: 0.0.1
Summary: Module for .vfg configs type
Home-page: https://woonworld.fun
Author: MrWoon
Author-email: vladpika51@gmail.com
Project-URL: Homepage, https://woonworld.fun
Project-URL: Documentation, https://github.com/MrWoonWorldT1/vconfig/issues/1
Keywords: vcfg vconfig config
Classifier: Programming Language :: Python :: 3.10
Classifier: License :: OSI Approved :: MIT License
Classifier: Operating System :: OS Independent
Requires-Python: >=3.7
Requires-Dist: requests (>=2.25.1)
